nlpbridge/__init__.py
nlpbridge/config.py
nlpbridge/nlp.py
nlpbridge/audio/__init__.py
nlpbridge/audio/_client.py
nlpbridge/audio/_exception.py
nlpbridge/audio/component.py
nlpbridge/audio/message.py
nlpbridge/audio/components/__init__.py
nlpbridge/audio/components/asr/__init__.py
nlpbridge/audio/components/asr/asr.py
nlpbridge/audio/components/asr/model.py
nlpbridge/audio/components/tts/__init__.py
nlpbridge/audio/components/tts/model.py
nlpbridge/audio/components/tts/tts.py
nlpbridge/audio/utils/__init__.py
nlpbridge/audio/utils/logger_util.py
nlpbridge/langchain_zhipuai/__init__.py
nlpbridge/langchain_zhipuai/embeddings/__init__.py
nlpbridge/langchain_zhipuai/embeddings/base.py
nlpbridge/persistent/__init__.py
nlpbridge/persistent/db.py
nlpbridge/persistent/db_crud.py
nlpbridge/persistent/mysql.py
nlpbridge/persistent/mysql_dataschema.py
nlpbridge/persistent/persistent_store.py
nlpbridge/persistent/redis.py
nlpbridge/text/__init__.py
nlpbridge/text/agent.py
nlpbridge/text/graph.py
nlpbridge/text/memory.py
nlpbridge/text/models.py
nlpbridge/text/router.py
nlpbridge/text/template_manager.py
nlpbridge/text/tools.py
tests/__init__.py
tests/text/__init__.py
tests/text/prompt.py
tests/text/test_FINAL_Agent.py
tests/text/test_agent.py
tests/text/test_agent_RAG.py
tests/text/test_agent_executor.py
tests/text/test_agent_fxy.py
tests/text/test_agent_with_memory.py
tests/text/test_chain.py
tests/text/test_graph.py
tests/text/test_graph_with_executor.py
tests/text/test_happyagent.py
tests/text/test_memory.py
tests/text/test_mysql.py
tests/text/test_nlp.py
tests/text/test_pickle.py
tests/text/test_prompt_fxy.py
tests/text/test_redis.py
tests/text/test_router_async.py
tests/text/test_template.py
tests/text/test_template_getter.py
tests/text/test_trouter.py
nlpbridge-0.6.1.dist-info/LICENSE
nlpbridge-0.6.1.dist-info/METADATA
nlpbridge-0.6.1.dist-info/WHEEL
nlpbridge-0.6.1.dist-info/entry_points.txt
nlpbridge-0.6.1.dist-info/top_level.txt
nlpbridge-0.6.1.dist-info/RECORD
